minchin/pelican/plugins/wikilinks/__init__.py
minchin/pelican/plugins/wikilinks/constants.py
minchin/pelican/plugins/wikilinks/regex.py
minchin/pelican/plugins/wikilinks/wikilinks.py
minchin_pelican_plugins_wikilinks-1.0.1.dist-info/licenses/LICENSE.txt
minchin_pelican_plugins_wikilinks-1.0.1.dist-info/METADATA
minchin_pelican_plugins_wikilinks-1.0.1.dist-info/WHEEL
minchin_pelican_plugins_wikilinks-1.0.1.dist-info/top_level.txt
minchin_pelican_plugins_wikilinks-1.0.1.dist-info/RECORD
