Metadata-Version: 2.4
Name: minchin.pelican.plugins.wikilinks
Version: 1.0.1
Summary: Support Wikilinks when generating Pelican sites
Author-email: William Minchin <w_minchin@hotmail.com>
Maintainer-email: William Minchin <w_minchin@hotmail.com>
License: MIT
Project-URL: Bug Tracker, https://github.com/MinchinWeb/minchin.pelican.plugins.wikilinks/issues
Project-URL: Repository, https://github.com/MinchinWeb/minchin.pelican.plugins.wikilinks
Keywords: pelican,plugin
Classifier: Development Status :: 5 - Production/Stable
Classifier: Environment :: Plugins
Classifier: Framework :: Pelican
Classifier: Framework :: Pelican :: Plugins
Classifier: Intended Audience :: End Users/Desktop
Classifier: Operating System :: OS Independent
Classifier: Topic :: Internet :: WWW/HTTP
Classifier: Topic :: Software Development :: Libraries :: Python Modules
License-File: LICENSE.txt
Requires-Dist: minchin.pelican.plugins.autoloader
Provides-Extra: dev
Requires-Dist: pip-tools; extra == "dev"
Requires-Dist: black; extra == "dev"
Requires-Dist: isort; extra == "dev"
Requires-Dist: minchin.releaser; extra == "dev"
Requires-Dist: invoke; extra == "dev"
Requires-Dist: pygments<=2.18.0; extra == "dev"
Dynamic: license-file
